stsynphot/__init__.py
stsynphot/catalog.py
stsynphot/config.py
stsynphot/exceptions.py
stsynphot/observationmode.py
stsynphot/spark.py
stsynphot/spectrum.py
stsynphot/spparser.py
stsynphot/stio.py
stsynphot/tables.py
stsynphot/version.py
stsynphot/wavetable.py
stsynphot/commissioning/__init__.py
stsynphot/commissioning/utils.py
stsynphot/commissioning/tests/__init__.py
stsynphot/commissioning/tests/test_acs_hrc.py
stsynphot/commissioning/tests/test_acs_sbc.py
stsynphot/commissioning/tests/test_acs_wfc.py
stsynphot/commissioning/tests/test_stis_ccd.py
stsynphot/commissioning/tests/test_stis_fuvmama.py
stsynphot/commissioning/tests/test_stis_nuvmama.py
stsynphot/commissioning/tests/test_wfc3_ir.py
stsynphot/commissioning/tests/test_wfc3_uvis1.py
stsynphot/commissioning/tests/test_wfc3_uvis2.py
stsynphot/commissioning/tests/data/HS20270651.dat
stsynphot/commissioning/tests/data/Zodi.fits
stsynphot/commissioning/tests/data/earthshine.fits
stsynphot/commissioning/tests/data/el1215a.fits
stsynphot/commissioning/tests/data/el1302a.fits
stsynphot/commissioning/tests/data/el1356a.fits
stsynphot/commissioning/tests/data/el2471a.fits
stsynphot/commissioning/tests/data/ngc1068_template.fits
stsynphot/commissioning/tests/data/qso_template.fits
stsynphot/data/detectors.dat
stsynphot/data/irafshortcuts.txt
stsynphot/data/wavecats/acs.dat
stsynphot/data/wavecats/acs_g800l_hrc.dat
stsynphot/data/wavecats/acs_g800l_wfc.dat
stsynphot/data/wavecats/acs_pr110l.dat
stsynphot/data/wavecats/acs_pr130l.dat
stsynphot/data/wavecats/acs_pr200l_hrc.dat
stsynphot/data/wavecats/cos_fuv_g130m_1291.txt
stsynphot/data/wavecats/cos_fuv_g130m_1300.txt
stsynphot/data/wavecats/cos_fuv_g130m_1309.txt
stsynphot/data/wavecats/cos_fuv_g130m_1318.txt
stsynphot/data/wavecats/cos_fuv_g130m_1327.txt
stsynphot/data/wavecats/cos_fuv_g140l_1105.txt
stsynphot/data/wavecats/cos_fuv_g140l_1230.txt
stsynphot/data/wavecats/cos_fuv_g140l_800.txt
stsynphot/data/wavecats/cos_fuv_g160m_1533.txt
stsynphot-1.4.0.dist-info/LICENSE
stsynphot-1.4.0.dist-info/METADATA
stsynphot-1.4.0.dist-info/WHEEL
stsynphot-1.4.0.dist-info/top_level.txt
stsynphot-1.4.0.dist-info/RECORD
