Metadata-Version: 2.1
Name: stsynphot
Version: 1.4.0
Summary: Synthetic photometry for HST
Home-page: https://www.github.com/spacetelescope/stsynphot_refactor
Author: STScI
Author-email: help@stsci.edu
License: BSD
Keywords: astronomy,astrophysics,synthetic,photometry,HST
Classifier: Intended Audience :: Science/Research
Classifier: License :: OSI Approved :: BSD License
Classifier: Operating System :: OS Independent
Classifier: Programming Language :: Python :: 3
Classifier: Programming Language :: Python :: Implementation :: CPython
Classifier: Topic :: Scientific/Engineering :: Astronomy
Classifier: Topic :: Scientific/Engineering :: Physics
Requires-Python: >=3.10
License-File: LICENSE
Requires-Dist: numpy>=1.23
Requires-Dist: astropy>=6
Requires-Dist: scipy>=1.9
Requires-Dist: synphot>=1.1
Requires-Dist: beautifulsoup4
Provides-Extra: all
Requires-Dist: matplotlib; extra == "all"
Provides-Extra: test
Requires-Dist: pytest-astropy; extra == "test"
Requires-Dist: ci-watson; extra == "test"
Provides-Extra: docs
Requires-Dist: sphinx-astropy; extra == "docs"
